uhlovodikovac/__init__.py
uhlovodikovac/exceptions.py
uhlovodikovac/functions.py
uhlovodikovac/hydrocarbons.jsonc
uhlovodikovac/main.py
uhlovodikovac-0.0.5.dist-info/LICENSE
uhlovodikovac-0.0.5.dist-info/METADATA
uhlovodikovac-0.0.5.dist-info/WHEEL
uhlovodikovac-0.0.5.dist-info/top_level.txt
uhlovodikovac-0.0.5.dist-info/RECORD
