Metadata-Version: 2.1
Name: uhlovodikovac
Version: 0.0.5
Summary: Package for Hydrocarbon to Image conversion
Home-page: https://github.com/bertik23/uhlovodikovac
Author: Bertik23
Author-email: bertikxxiii@gmail.com
License: UNKNOWN
Platform: UNKNOWN
Classifier: Programming Language :: Python :: 3
Classifier: License :: OSI Approved :: MIT License
Classifier: Operating System :: OS Independent
Requires-Python: >=3.7
Requires-Dist: Pillow (~=8.0.0)
Requires-Dist: numpy (~=1.17.0)
